imgtools_cli/__init__.py
imgtools_cli/__main__.py
imgtools_cli/autocrop.py
imgtools_cli/download.py
imgtools_cli/hassan_people_remover.py
imgtools_cli/image2chunks.py
imgtools_cli/image2png.py
imgtools_cli/image_resize.py
imgtools_cli-1.0.8.dist-info/LICENSE
imgtools_cli-1.0.8.dist-info/METADATA
imgtools_cli-1.0.8.dist-info/WHEEL
imgtools_cli-1.0.8.dist-info/entry_points.txt
imgtools_cli-1.0.8.dist-info/top_level.txt
imgtools_cli-1.0.8.dist-info/RECORD
