Metadata-Version: 2.1
Name: imgtools-cli
Version: 1.0.8
Summary: a command line interface for preparing image models
Home-page: https://github.com/3ee-Games/image-tools
Author: 3ee Games
Author-email: ryguy@3ee.com
Project-URL: Homepage, https://3ee.com
Project-URL: Suppport, https://ko-fi.com/3eegames
Project-URL: Source, https://github.com/3ee-Games/image-tools
Project-URL: Tracker, https://github.com/3ee-Games/image-tools/issues
Keywords: image-downloader,image-scraper,heic,hypernetwork,heic-to-png,stable-diffusion,textual-inversion,dreambooth,image-chunks,image-chunker
Classifier: Development Status :: 4 - Beta
Classifier: Intended Audience :: Developers
Classifier: License :: OSI Approved :: MIT License
Classifier: Programming Language :: Python :: 3.10
Classifier: Programming Language :: Python :: 3.6
Classifier: Programming Language :: Python :: 3.7
Classifier: Programming Language :: Python :: 3.8
Classifier: Programming Language :: Python :: 3.9
Classifier: Topic :: Software Development
License-File: LICENSE
Requires-Dist: beautifulsoup4 (==4.11.1)
Requires-Dist: urllib3 (==1.26.13)
Requires-Dist: Pillow (==9.3.0)
Requires-Dist: argparse-ext
Requires-Dist: pillow-heif (==0.9.0)
Requires-Dist: opencv-python
Requires-Dist: requests
